aws_durable_execution_sdk_python_testing/__about__.py
aws_durable_execution_sdk_python_testing/__init__.py
aws_durable_execution_sdk_python_testing/cli.py
aws_durable_execution_sdk_python_testing/client.py
aws_durable_execution_sdk_python_testing/exceptions.py
aws_durable_execution_sdk_python_testing/execution.py
aws_durable_execution_sdk_python_testing/executor.py
aws_durable_execution_sdk_python_testing/invoker.py
aws_durable_execution_sdk_python_testing/model.py
aws_durable_execution_sdk_python_testing/observer.py
aws_durable_execution_sdk_python_testing/py.typed
aws_durable_execution_sdk_python_testing/runner.py
aws_durable_execution_sdk_python_testing/scheduler.py
aws_durable_execution_sdk_python_testing/token.py
aws_durable_execution_sdk_python_testing/checkpoint/__init__.py
aws_durable_execution_sdk_python_testing/checkpoint/processor.py
aws_durable_execution_sdk_python_testing/checkpoint/transformer.py
aws_durable_execution_sdk_python_testing/checkpoint/processors/__init__.py
aws_durable_execution_sdk_python_testing/checkpoint/processors/base.py
aws_durable_execution_sdk_python_testing/checkpoint/processors/callback.py
aws_durable_execution_sdk_python_testing/checkpoint/processors/context.py
aws_durable_execution_sdk_python_testing/checkpoint/processors/execution.py
aws_durable_execution_sdk_python_testing/checkpoint/processors/step.py
aws_durable_execution_sdk_python_testing/checkpoint/processors/wait.py
aws_durable_execution_sdk_python_testing/checkpoint/validators/__init__.py
aws_durable_execution_sdk_python_testing/checkpoint/validators/checkpoint.py
aws_durable_execution_sdk_python_testing/checkpoint/validators/transitions.py
aws_durable_execution_sdk_python_testing/checkpoint/validators/operations/__init__.py
aws_durable_execution_sdk_python_testing/checkpoint/validators/operations/callback.py
aws_durable_execution_sdk_python_testing/checkpoint/validators/operations/context.py
aws_durable_execution_sdk_python_testing-1.1.1.dist-info/METADATA
aws_durable_execution_sdk_python_testing-1.1.1.dist-info/WHEEL
aws_durable_execution_sdk_python_testing-1.1.1.dist-info/entry_points.txt
aws_durable_execution_sdk_python_testing-1.1.1.dist-info/licenses/LICENSE
aws_durable_execution_sdk_python_testing-1.1.1.dist-info/licenses/NOTICE
aws_durable_execution_sdk_python_testing-1.1.1.dist-info/RECORD
