Metadata-Version: 2.4
Name: aws-durable-execution-sdk-python-testing
Version: 1.1.1
Summary: AWS Durable Execution Testing SDK for Python
Project-URL: Documentation, https://github.com/aws/aws-durable-execution-sdk-python-testing#readme
Project-URL: Issues, https://github.com/aws/aws-durable-execution-sdk-python-testing/issues
Project-URL: Source, https://github.com/aws/aws-durable-execution-sdk-python-testing
Author-email: yaythomas <tgaigher@amazon.com>
License-Expression: Apache-2.0
License-File: LICENSE
License-File: NOTICE
Classifier: Development Status :: 4 - Beta
Classifier: Programming Language :: Python
Classifier: Programming Language :: Python :: 3.11
Classifier: Programming Language :: Python :: 3.12
Classifier: Programming Language :: Python :: 3.13
Classifier: Programming Language :: Python :: 3.14
Classifier: Programming Language :: Python :: Implementation :: CPython
Classifier: Programming Language :: Python :: Implementation :: PyPy
Requires-Python: >=3.11
Requires-Dist: aws-durable-execution-sdk-python>=1.0.0
Requires-Dist: boto3>=1.42.1
Requires-Dist: requests>=2.25.0
